odoo/addons/product_import_ubl/README.rst
odoo/addons/product_import_ubl/__init__.py
odoo/addons/product_import_ubl/__manifest__.py
odoo/addons/product_import_ubl/i18n/it.po
odoo/addons/product_import_ubl/i18n/product_import_ubl.pot
odoo/addons/product_import_ubl/readme/CONTRIBUTORS.rst
odoo/addons/product_import_ubl/readme/DESCRIPTION.rst
odoo/addons/product_import_ubl/static/description/icon.png
odoo/addons/product_import_ubl/static/description/index.html
odoo/addons/product_import_ubl/tests/__init__.py
odoo/addons/product_import_ubl/tests/common.py
odoo/addons/product_import_ubl/tests/test_ubl_catalogue_import.py
odoo/addons/product_import_ubl/tests/files/UBL-Catalogue_Example.xml
odoo/addons/product_import_ubl/tests/files/UBL-Catalogue_Example2.xml
odoo/addons/product_import_ubl/wizard/__init__.py
odoo/addons/product_import_ubl/wizard/product_import.py
odoo14_addon_product_import_ubl-14.0.1.2.1.dist-info/METADATA
odoo14_addon_product_import_ubl-14.0.1.2.1.dist-info/WHEEL
odoo14_addon_product_import_ubl-14.0.1.2.1.dist-info/top_level.txt
odoo14_addon_product_import_ubl-14.0.1.2.1.dist-info/RECORD
